{
  "DEV": {
    "URL": "https://unity-dev.qcnet.com/",
   
    "AccUserManager": "gopal_patil+AUM@bio-rad.com",
    "LabUserManager": "gopal_patil+LabUserManager_1@bio-rad.com",
    "LabSupervisor": "gopal_patil+LabSupervisor_1@bio-rad.com",
    "LeadTechRole": "gopal_patil+LeadTechnician_1@bio-rad.com",
    "TechRole": "gopal_patil+Technician_1@bio-rad.com",
    "LotViewrSales": "vinayak_yadav+LotViewerSales@bio-rad.com",
    "BioRadManager": "gopal_patil+BRM_1@bio-rad.com",
    "AUM_LS": "gopal_patil+AUM_LabSupervisor@bio-rad.com",
    "AUM_LUM_LS": "gopal_patil+AUM_LUM_LabSupervisor@bio-rad.com",
    "LUM_LS": "gopal_patil+LUM_LS@bio-rad.com",
    "LUM_LT": "gopal_patil+LUM_LeadTech@bio-rad.com",
    "LUM_T": "gopal_patil+LUM_Tech@bio-rad.com",
    "CTSUser": "gopal_patil+CTS_1@bio-rad.com",
    "Password": "Welcome1",
    "FirstName": "Gopal",
    "LastName": "Patil",
    "BRM+CTSUser": "gopal_patil+BRM_CTS@bio-rad.com",
    "Department": "CompleteDept",
    "Instrument": "AU480",
    "Control": "Pediatric",
    "Analyte": "Calcium",
    "DepartmentWithoughtInstrument": "DeptWithought_INS",
    "DepartmentWithoughtAnalyte": "Auto_NoAnalyte",
    "DepartmentWithoughtAnalyteAndControl": "DeptWithoughtControlAndAnalyte",
    "NewDeptName1": "Automation",
    "editDeptName": "AutomationEditLab",
    "NewDepTempName1": "TempEditDept",
    "NewInstManufacturer1": "Beckman Coulter",
    "NewInstModel1": "AU480",
    "NewInstCustomName": "InstruCustomName",
    "NewControlCustomName": "ControlCustomName",
    "NewInstSerialNum1": "Serial007",
    "NewControlName1": "Pediatric",
    "NewControlLotNumber1": "44370",
    "NewAnalyte1": "Calcium",
    "NewAnalyteReagent1": "CA",
    "NewAnalyteCalibrator1": "Urine Cal B64606",
    "NewAnalyteMethod": "Arsenazo III",
    "NewAnalyteUnit": "mmol/L",
    "levels": "2" 
  },
  "QA": {
    "URL": "https://unity-test.qcnet.com/"
   },
  "STAGE": {}
}